{
  "trace_authority": {
    "usage": "TraceAuthority.generate() or TraceAuthority.propagate()",
    "stages": ["Market", "Feature", "Signal", "Risk", "Execution", "OMS", "Fill"]
  },
  "config_manager": {
    "usage": "self.config_manager.get()",
    "stages": ["Risk", "Execution"]
  },
  "fail_fast_engine": {
    "usage": "self.fail_fast_engine.handle_error()",
    "stages": ["All production handlers"]
  },
  "logger": {
    "usage": "logger.bind(trace_id=trace_id)",
    "stages": ["All production handlers"]
  },
  "decimal_adapter": {
    "usage": "math_authority.d() and quantization methods",
    "stages": ["Market", "Signal", "Risk", "Execution", "Fill"]
  }
}
